AUTHORS
COPYING
MANIFEST.in
ez_setup.py
setup.py
bin/ldaptool
contrib/ldaptool-0.1.ebuild
doc/Makefile
doc/conf.py
doc/dev.rst
doc/index.rst
doc/introduction.rst
doc/ldaptool.8
doc/license.rst
doc/mod-commands.rst
doc/mod-ldap.rst
doc/mod-ldaptool.rst
doc/user-config.rst
doc/user-usage.rst
doc/user.rst
doc/ext/__init__.py
doc/ext/builders.py
doc/ext/configwriter.py
doc/ext/directives.py
doc/static/style.css
ldaptool/__init__.py
ldaptool/accounts.py
ldaptool/ldap.py
ldaptool/settings.py
ldaptool/version.py
ldaptool.egg-info/PKG-INFO
ldaptool.egg-info/SOURCES.txt
ldaptool.egg-info/dependency_links.txt
ldaptool.egg-info/top_level.txt
ldaptool/commands/__init__.py
ldaptool/commands/accounts.py
ldaptool/commands/console.py
ldaptool/commands/core.py
ldaptool/util/__init__.py
ldaptool/util/i18n.py
ldaptool/util/messaging.py
ldaptool/util/misc.py
ldaptool/util/optparse.py
tests/__init__.py
tests/test_commands_accounts.py
tests/test_commands_console.py
tests/test_ldap.py
tests/test_settings.py
tests/test_util_misc.py