Metadata-Version: 1.0
Name: ldaptool
Version: 0.1
Summary: Tool for manipulating LDAP databases
Home-page: http://www.ox9.org/projects/ldaptool/
Author: Philipp Bunge
Author-email: buge@crimson.ch
License: GNU General Public License (GPL)
Platform: any
Classifier: Development Status :: 3 - Alpha
Classifier: Intended Audience :: System Administrators
Classifier: License :: OSI Approved :: GNU General Public License (GPL)
Classifier: Operating System :: OS Independent
Classifier: Programming Language :: Python
